futurehouse_mcp/__init__.py
futurehouse_mcp/server.py
futurehouse_mcp-0.2.0.dist-info/WHEEL
futurehouse_mcp-0.2.0.dist-info/entry_points.txt
futurehouse_mcp-0.2.0.dist-info/METADATA
futurehouse_mcp-0.2.0.dist-info/RECORD
